Encrypto/Encrypto.py
Encrypto/__init__.py
Encrypto-0.0.4.dist-info/LICENSE.txt
Encrypto-0.0.4.dist-info/METADATA
Encrypto-0.0.4.dist-info/WHEEL
Encrypto-0.0.4.dist-info/top_level.txt
Encrypto-0.0.4.dist-info/RECORD
