Metadata-Version: 2.1
Name: Encrypto
Version: 0.0.4
Summary: Encrypting strings
Home-page: UNKNOWN
Author: Moritz Schittenhelm
Author-email: moritz5911@gmail.com
License: UNKNOWN
Keywords: python,Encrypto,encryption,coding
Platform: UNKNOWN
Classifier: Intended Audience :: Developers
Classifier: Programming Language :: Python :: 3
Classifier: Operating System :: Unix
Classifier: Operating System :: MacOS :: MacOS X
Classifier: Operating System :: Microsoft :: Windows
